[
  {
    "orderId": "REST-001",
    "tableId": "TABLE-5", 
    "items": ["Burger", "Fries"],
    "orderTime": "18:30",
    "deliveryTime": "19:00",
    "priority": "HIGH"
  },
  {
    "orderId": "REST-002",
    "tableId": "TABLE-3",
    "items": ["Pizza"], 
    "orderTime": "18:45",
    "deliveryTime": "18:55",
    "priority": "HIGH"
  },
  {
    "orderId": "REST-003",
    "tableId": "TABLE-7",
    "items": ["Salad"],
    "orderTime": "18:20", 
    "deliveryTime": "19:30",
    "priority": "LOW"
  }
]